nanoyc/logging/__init__.py
nanoyc/ydb/__init__.py
nanoydb-0.1.0.dist-info/LICENSE.txt
nanoydb-0.1.0.dist-info/METADATA
nanoydb-0.1.0.dist-info/WHEEL
nanoydb-0.1.0.dist-info/top_level.txt
nanoydb-0.1.0.dist-info/RECORD
