Metadata-Version: 2.1
Name: nanoydb
Version: 0.1.0
Summary: A nano package for working with YDB Yandex Serverless Database
Author: Dima Frolenko
Author-email: orangefrol@gmail.com
License: LICENSE.txt
License-File: LICENSE.txt
Requires-Dist: ydb[yc]
